envoy_utils/__init__.py
envoy_utils/enphaseStreamMeter.py
envoy_utils/envoy_utils.py
envoy_utils/findEnphaseWithBonjour.py
envoy_utils/passwordCalc.py
envoy_utils-0.0.1.dist-info/LICENSE
envoy_utils-0.0.1.dist-info/METADATA
envoy_utils-0.0.1.dist-info/WHEEL
envoy_utils-0.0.1.dist-info/top_level.txt
envoy_utils-0.0.1.dist-info/RECORD
